[{"name":"観光列車","company":"富士急行","lastupdate_gmt":1646061145,"source":"鉄道com RSS"},{"name":"貝塚線","company":"西日本鉄道","lastupdate_gmt":1646061311,"source":"鉄道com RSS"},{"name":"天神大牟田線","company":"西日本鉄道","lastupdate_gmt":1646061311,"source":"鉄道com RSS"},{"name":"特急ラピート","company":"南海電気鉄道","lastupdate_gmt":1646061303,"source":"鉄道com RSS"},{"name":"天竜浜名湖線","company":"天竜浜名湖鉄道","lastupdate_gmt":1646061325,"source":"鉄道com RSS"},{"name":"高山線","company":"JR東海","lastupdate_gmt":1646061318,"source":"鉄道com RSS"},{"name":"木次線","company":"JR西日本","lastupdate_gmt":1646061312,"source":"鉄道com RSS"},{"name":"只見線","company":"JR東日本","lastupdate_gmt":1646061307,"source":"鉄道com RSS"},{"name":"飯山線","company":"JR東日本","lastupdate_gmt":1646061307,"source":"鉄道com RSS"},{"name":"上高地線","company":"アルピコ交通","lastupdate_gmt":1646060479,"source":"鉄道com RSS"}]