[{"name":"観光列車","company":"富士急行","lastupdate_gmt":1625204891,"source":"鉄道com RSS"},{"name":"浅草線","company":"都営地下鉄","lastupdate_gmt":1625204890,"source":"鉄道com RSS"},{"name":"伊豆急行線","company":"伊豆急行","lastupdate_gmt":1625204890,"source":"鉄道com RSS"},{"name":"伊東線","company":"JR東日本","lastupdate_gmt":1625204888,"source":"鉄道com RSS"},{"name":"東海道線","company":"JR東日本","lastupdate_gmt":1625204888,"source":"鉄道com RSS"},{"name":"宇都宮線","company":"JR東日本","lastupdate_gmt":1625204888,"source":"鉄道com RSS"},{"name":"高崎線","company":"JR東日本","lastupdate_gmt":1625204888,"source":"鉄道com RSS"},{"name":"常磐線快速電車","company":"JR東日本","lastupdate_gmt":1625204888,"source":"鉄道com RSS"},{"name":"常磐線各駅停車","company":"JR東日本","lastupdate_gmt":1625204888,"source":"鉄道com RSS"},{"name":"常磐線","company":"JR東日本","lastupdate_gmt":1625204888,"source":"鉄道com RSS"},{"name":"京急線","company":"京急電鉄","lastupdate_gmt":1625204708,"source":"鉄道com RSS"},{"name":"大師線","company":"京急電鉄","lastupdate_gmt":1625204708,"source":"鉄道com RSS"},{"name":"奈良線","company":"JR西日本","lastupdate_gmt":1625204712,"source":"鉄道com RSS"},{"name":"きのくに線","company":"JR西日本","lastupdate_gmt":1625204712,"source":"鉄道com RSS"},{"name":"特急ラピート","company":"南海電気鉄道","lastupdate_gmt":1625204710,"source":"鉄道com RSS"},{"name":"特急サザン","company":"南海電気鉄道","lastupdate_gmt":1625204710,"source":"鉄道com RSS"},{"name":"駿豆線","company":"伊豆箱根鉄道","lastupdate_gmt":1625204891,"source":"鉄道com RSS"},{"name":"東海道線（名古屋地区）","company":"JR東海","lastupdate_gmt":1625204718,"source":"鉄道com RSS"},{"name":"紀勢線","company":"JR東海","lastupdate_gmt":1625204718,"source":"鉄道com RSS"},{"name":"飯田線","company":"JR東海","lastupdate_gmt":1625204718,"source":"鉄道com RSS"},{"name":"東海道線（静岡地区）","company":"JR東海","lastupdate_gmt":1625204718,"source":"鉄道com RSS"},{"name":"身延線","company":"JR東海","lastupdate_gmt":1625204718,"source":"鉄道com RSS"},{"name":"御殿場線","company":"JR東海","lastupdate_gmt":1625204718,"source":"鉄道com RSS"},{"name":"常滑線","company":"名古屋鉄道","lastupdate_gmt":1625204709,"source":"鉄道com RSS"},{"name":"名古屋本線","company":"名古屋鉄道","lastupdate_gmt":1625204709,"source":"鉄道com RSS"},{"name":"北陸本線","company":"JR西日本","lastupdate_gmt":1625204711,"source":"鉄道com RSS"},{"name":"函館本線","company":"JR北海道","lastupdate_gmt":1625204704,"source":"鉄道com RSS"},{"name":"学園都市線","company":"JR北海道","lastupdate_gmt":1625204704,"source":"鉄道com RSS"},{"name":"千歳線","company":"JR北海道","lastupdate_gmt":1625204704,"source":"鉄道com RSS"}]