[{"name":"観光列車","company":"富士急行","lastupdate_gmt":1647876971,"source":"鉄道com RSS"},{"name":"阿武隈急行線","company":"阿武隈急行","lastupdate_gmt":1647876968,"source":"鉄道com RSS"},{"name":"木次線","company":"JR西日本","lastupdate_gmt":1647876920,"source":"鉄道com RSS"},{"name":"山陽本線","company":"JR西日本","lastupdate_gmt":1647876920,"source":"鉄道com RSS"},{"name":"呉線","company":"JR西日本","lastupdate_gmt":1647876920,"source":"鉄道com RSS"},{"name":"只見線","company":"JR東日本","lastupdate_gmt":1647876906,"source":"鉄道com RSS"},{"name":"篠ノ井線","company":"JR東日本","lastupdate_gmt":1647876906,"source":"鉄道com RSS"},{"name":"五能線","company":"JR東日本","lastupdate_gmt":1647876905,"source":"鉄道com RSS"},{"name":"羽越本線","company":"JR東日本","lastupdate_gmt":1647876905,"source":"鉄道com RSS"},{"name":"常磐線","company":"JR東日本","lastupdate_gmt":1647876905,"source":"鉄道com RSS"},{"name":"東北本線","company":"JR東日本","lastupdate_gmt":1647876905,"source":"鉄道com RSS"},{"name":"上高地線","company":"アルピコ交通","lastupdate_gmt":1647876637,"source":"鉄道com RSS"}]