[{"name":"上越線","company":"JR東日本","lastupdate_gmt":1644308281,"source":"鉄道com RSS"},{"name":"京浜東北線","company":"JR東日本","lastupdate_gmt":1644308281,"source":"鉄道com RSS"},{"name":"宇都宮線","company":"JR東日本","lastupdate_gmt":1644308281,"source":"鉄道com RSS"},{"name":"東海道線","company":"JR東日本","lastupdate_gmt":1644308281,"source":"鉄道com RSS"},{"name":"高崎線","company":"JR東日本","lastupdate_gmt":1644308281,"source":"鉄道com RSS"},{"name":"総武快速線","company":"JR東日本","lastupdate_gmt":1644308281,"source":"鉄道com RSS"},{"name":"山手線","company":"JR東日本","lastupdate_gmt":1644308281,"source":"鉄道com RSS"},{"name":"埼京線","company":"JR東日本","lastupdate_gmt":1644308281,"source":"鉄道com RSS"},{"name":"川越線","company":"JR東日本","lastupdate_gmt":1644308281,"source":"鉄道com RSS"},{"name":"中央･総武各駅停車","company":"JR東日本","lastupdate_gmt":1644308281,"source":"鉄道com RSS"},{"name":"中央線快速電車","company":"JR東日本","lastupdate_gmt":1644308281,"source":"鉄道com RSS"},{"name":"中央本線","company":"JR東日本","lastupdate_gmt":1644308281,"source":"鉄道com RSS"},{"name":"常磐線快速電車","company":"JR東日本","lastupdate_gmt":1644308281,"source":"鉄道com RSS"},{"name":"常磐線各駅停車","company":"JR東日本","lastupdate_gmt":1644308281,"source":"鉄道com RSS"},{"name":"常磐線","company":"JR東日本","lastupdate_gmt":1644308281,"source":"鉄道com RSS"},{"name":"横須賀線","company":"JR東日本","lastupdate_gmt":1644308281,"source":"鉄道com RSS"},{"name":"京葉線","company":"JR東日本","lastupdate_gmt":1644308281,"source":"鉄道com RSS"},{"name":"武蔵野線","company":"JR東日本","lastupdate_gmt":1644308281,"source":"鉄道com RSS"},{"name":"八高線","company":"JR東日本","lastupdate_gmt":1644308281,"source":"鉄道com RSS"},{"name":"五日市線","company":"JR東日本","lastupdate_gmt":1644308281,"source":"鉄道com RSS"},{"name":"青梅線","company":"JR東日本","lastupdate_gmt":1644308281,"source":"鉄道com RSS"},{"name":"伊東線","company":"JR東日本","lastupdate_gmt":1644308281,"source":"鉄道com RSS"},{"name":"相模線","company":"JR東日本","lastupdate_gmt":1644308281,"source":"鉄道com RSS"},{"name":"横浜線","company":"JR東日本","lastupdate_gmt":1644308281,"source":"鉄道com RSS"},{"name":"南武線","company":"JR東日本","lastupdate_gmt":1644308281,"source":"鉄道com RSS"},{"name":"鶴見線","company":"JR東日本","lastupdate_gmt":1644308281,"source":"鉄道com RSS"},{"name":"日光線","company":"JR東日本","lastupdate_gmt":1644308281,"source":"鉄道com RSS"},{"name":"烏山線","company":"JR東日本","lastupdate_gmt":1644308281,"source":"鉄道com RSS"},{"name":"上野東京ライン","company":"JR東日本","lastupdate_gmt":1644308281,"source":"鉄道com RSS"},{"name":"相鉄線直通列車","company":"JR東日本","lastupdate_gmt":1644308281,"source":"鉄道com RSS"},{"name":"湘南新宿ライン","company":"JR東日本","lastupdate_gmt":1644308281,"source":"鉄道com RSS"},{"name":"観光列車","company":"富士急行","lastupdate_gmt":1644307931,"source":"鉄道com RSS"},{"name":"天神大牟田線","company":"西日本鉄道","lastupdate_gmt":1644308112,"source":"鉄道com RSS"},{"name":"貝塚線","company":"西日本鉄道","lastupdate_gmt":1644308112,"source":"鉄道com RSS"},{"name":"鹿児島本線","company":"JR九州","lastupdate_gmt":1644308107,"source":"鉄道com RSS"},{"name":"久大本線","company":"JR九州","lastupdate_gmt":1644308107,"source":"鉄道com RSS"},{"name":"日豊本線","company":"JR九州","lastupdate_gmt":1644308107,"source":"鉄道com RSS"},{"name":"近江鉄道線","company":"近江鉄道","lastupdate_gmt":1644308133,"source":"鉄道com RSS"},{"name":"御堂筋線","company":"大阪メトロ","lastupdate_gmt":1644308113,"source":"鉄道com RSS"},{"name":"特急ラピート","company":"南海電気鉄道","lastupdate_gmt":1644308110,"source":"鉄道com RSS"},{"name":"特急サザン","company":"南海電気鉄道","lastupdate_gmt":1644308110,"source":"鉄道com RSS"},{"name":"養老線","company":"養老鉄道","lastupdate_gmt":1644307260,"source":"鉄道com RSS"},{"name":"郊外電車","company":"伊予鉄道","lastupdate_gmt":1644308132,"source":"鉄道com RSS"},{"name":"木次線","company":"JR西日本","lastupdate_gmt":1644308112,"source":"鉄道com RSS"},{"name":"羽越本線","company":"JR東日本","lastupdate_gmt":1644308107,"source":"鉄道com RSS"},{"name":"飯山線","company":"JR東日本","lastupdate_gmt":1644308107,"source":"鉄道com RSS"},{"name":"津軽線","company":"JR東日本","lastupdate_gmt":1644308105,"source":"鉄道com RSS"},{"name":"五能線","company":"JR東日本","lastupdate_gmt":1644308105,"source":"鉄道com RSS"},{"name":"花輪線","company":"JR東日本","lastupdate_gmt":1644308105,"source":"鉄道com RSS"},{"name":"函館本線","company":"JR北海道","lastupdate_gmt":1644308103,"source":"鉄道com RSS"},{"name":"学園都市線","company":"JR北海道","lastupdate_gmt":1644308103,"source":"鉄道com RSS"},{"name":"千歳線","company":"JR北海道","lastupdate_gmt":1644308103,"source":"鉄道com RSS"},{"name":"石勝線","company":"JR北海道","lastupdate_gmt":1644308103,"source":"鉄道com RSS"},{"name":"室蘭本線","company":"JR北海道","lastupdate_gmt":1644308103,"source":"鉄道com RSS"},{"name":"根室本線","company":"JR北海道","lastupdate_gmt":1644308103,"source":"鉄道com RSS"},{"name":"上高地線","company":"アルピコ交通","lastupdate_gmt":1644307257,"source":"鉄道com RSS"}]