[{"name":"観光列車","company":"富士急行","lastupdate_gmt":1645850891,"source":"鉄道com RSS"},{"name":"上越線","company":"JR東日本","lastupdate_gmt":1645850888,"source":"鉄道com RSS"},{"name":"東海道線","company":"JR東日本","lastupdate_gmt":1645850888,"source":"鉄道com RSS"},{"name":"上野東京ライン","company":"JR東日本","lastupdate_gmt":1645850888,"source":"鉄道com RSS"},{"name":"湘南新宿ライン","company":"JR東日本","lastupdate_gmt":1645850888,"source":"鉄道com RSS"},{"name":"宇都宮線","company":"JR東日本","lastupdate_gmt":1645850888,"source":"鉄道com RSS"},{"name":"日光線特急","company":"東武鉄道","lastupdate_gmt":1645850708,"source":"鉄道com RSS"},{"name":"貝塚線","company":"西日本鉄道","lastupdate_gmt":1645850712,"source":"鉄道com RSS"},{"name":"天神大牟田線","company":"西日本鉄道","lastupdate_gmt":1645850712,"source":"鉄道com RSS"},{"name":"奈良線","company":"JR西日本","lastupdate_gmt":1645850712,"source":"鉄道com RSS"},{"name":"飯田線","company":"JR東海","lastupdate_gmt":1645850739,"source":"鉄道com RSS"},{"name":"北しなの線","company":"しなの鉄道","lastupdate_gmt":1645850737,"source":"鉄道com RSS"},{"name":"ほくほく線","company":"北越急行","lastupdate_gmt":1645850715,"source":"鉄道com RSS"},{"name":"木次線","company":"JR西日本","lastupdate_gmt":1645850712,"source":"鉄道com RSS"},{"name":"只見線","company":"JR東日本","lastupdate_gmt":1645850707,"source":"鉄道com RSS"},{"name":"五能線","company":"JR東日本","lastupdate_gmt":1645850705,"source":"鉄道com RSS"},{"name":"仙山線","company":"JR東日本","lastupdate_gmt":1645850705,"source":"鉄道com RSS"},{"name":"函館本線","company":"JR北海道","lastupdate_gmt":1645850703,"source":"鉄道com RSS"},{"name":"千歳線","company":"JR北海道","lastupdate_gmt":1645850703,"source":"鉄道com RSS"},{"name":"石勝線","company":"JR北海道","lastupdate_gmt":1645850703,"source":"鉄道com RSS"},{"name":"室蘭本線","company":"JR北海道","lastupdate_gmt":1645850703,"source":"鉄道com RSS"},{"name":"上高地線","company":"アルピコ交通","lastupdate_gmt":1645849839,"source":"鉄道com RSS"}]