[{"name":"観光列車","company":"富士急行","lastupdate_gmt":1634698091,"source":"鉄道com RSS"},{"name":"湘南新宿ライン","company":"JR東日本","lastupdate_gmt":1634698089,"source":"鉄道com RSS"},{"name":"横須賀線","company":"JR東日本","lastupdate_gmt":1634698089,"source":"鉄道com RSS"},{"name":"石清水八幡宮参道ケーブル","company":"京阪電気鉄道","lastupdate_gmt":1634698103,"source":"鉄道com RSS"},{"name":"特急ラピート","company":"南海電気鉄道","lastupdate_gmt":1634697909,"source":"鉄道com RSS"},{"name":"特急サザン","company":"南海電気鉄道","lastupdate_gmt":1634697909,"source":"鉄道com RSS"},{"name":"飯田線","company":"JR東海","lastupdate_gmt":1634697918,"source":"鉄道com RSS"},{"name":"あいの風とやま鉄道線","company":"あいの風とやま鉄道","lastupdate_gmt":1634697927,"source":"鉄道com RSS"},{"name":"山口線","company":"JR西日本","lastupdate_gmt":1634697911,"source":"鉄道com RSS"},{"name":"芸備線","company":"JR西日本","lastupdate_gmt":1634697911,"source":"鉄道com RSS"},{"name":"土讃線","company":"JR四国","lastupdate_gmt":1634697907,"source":"鉄道com RSS"},{"name":"篠ノ井線","company":"JR東日本","lastupdate_gmt":1634697906,"source":"鉄道com RSS"},{"name":"中央本線","company":"JR東日本","lastupdate_gmt":1634697906,"source":"鉄道com RSS"},{"name":"米坂線","company":"JR東日本","lastupdate_gmt":1634697906,"source":"鉄道com RSS"},{"name":"越後線","company":"JR東日本","lastupdate_gmt":1634697906,"source":"鉄道com RSS"},{"name":"羽越本線","company":"JR東日本","lastupdate_gmt":1634697906,"source":"鉄道com RSS"},{"name":"函館本線","company":"JR北海道","lastupdate_gmt":1634697904,"source":"鉄道com RSS"},{"name":"千歳線","company":"JR北海道","lastupdate_gmt":1634697904,"source":"鉄道com RSS"},{"name":"釧網本線","company":"JR北海道","lastupdate_gmt":1634697904,"source":"鉄道com RSS"},{"name":"花輪線","company":"JR東日本","lastupdate_gmt":1634697904,"source":"鉄道com RSS"},{"name":"東北本線","company":"JR東日本","lastupdate_gmt":1634697904,"source":"鉄道com RSS"},{"name":"上高地線","company":"アルピコ交通","lastupdate_gmt":1634697039,"source":"鉄道com RSS"}]