[{"name":"","company":"富士急行線","lastupdate_gmt":1652355371,"source":"鉄道com RSS"},{"name":"ブルーライン","company":"横浜市営地下鉄","lastupdate_gmt":1652355303,"source":"鉄道com RSS"},{"name":"長崎本線","company":"JR九州","lastupdate_gmt":1652355305,"source":"鉄道com RSS"},{"name":"東海道線（名古屋地区）","company":"JR東海","lastupdate_gmt":1652355317,"source":"鉄道com RSS"},{"name":"身延線","company":"JR東海","lastupdate_gmt":1652355317,"source":"鉄道com RSS"},{"name":"阿武隈急行線","company":"阿武隈急行","lastupdate_gmt":1652355368,"source":"鉄道com RSS"},{"name":"上高地線","company":"アルピコ交通","lastupdate_gmt":1652355040,"source":"鉄道com RSS"}]