[{"name":"京葉線","company":"JR東日本","lastupdate_gmt":1639271341,"source":"鉄道com RSS"},{"name":"武蔵野線","company":"JR東日本","lastupdate_gmt":1639271341,"source":"鉄道com RSS"},{"name":"観光列車","company":"富士急行","lastupdate_gmt":1639270842,"source":"鉄道com RSS"},{"name":"ユーカリが丘線","company":"山万","lastupdate_gmt":1639270805,"source":"鉄道com RSS"},{"name":"日南線","company":"JR九州","lastupdate_gmt":1639271105,"source":"鉄道com RSS"},{"name":"千歳線","company":"JR北海道","lastupdate_gmt":1639271103,"source":"鉄道com RSS"},{"name":"上高地線","company":"アルピコ交通","lastupdate_gmt":1639270854,"source":"鉄道com RSS"}]