[{"name":"京浜東北線","company":"JR東日本","lastupdate_gmt":1635059882,"source":"鉄道com RSS"},{"name":"相鉄線直通列車","company":"JR東日本","lastupdate_gmt":1635059882,"source":"鉄道com RSS"},{"name":"埼京線","company":"JR東日本","lastupdate_gmt":1635059882,"source":"鉄道com RSS"},{"name":"山手線","company":"JR東日本","lastupdate_gmt":1635059882,"source":"鉄道com RSS"},{"name":"宇都宮線","company":"JR東日本","lastupdate_gmt":1635059882,"source":"鉄道com RSS"},{"name":"日光線","company":"JR東日本","lastupdate_gmt":1635059882,"source":"鉄道com RSS"},{"name":"千代田線","company":"東京メトロ","lastupdate_gmt":1635059725,"source":"鉄道com RSS"},{"name":"特急ロマンスカー","company":"小田急電鉄","lastupdate_gmt":1635059709,"source":"鉄道com RSS"},{"name":"小田原線","company":"小田急電鉄","lastupdate_gmt":1635059709,"source":"鉄道com RSS"},{"name":"観光列車","company":"富士急行","lastupdate_gmt":1635059529,"source":"鉄道com RSS"},{"name":"ユーカリが丘線","company":"山万","lastupdate_gmt":1635058805,"source":"鉄道com RSS"},{"name":"石清水八幡宮参道ケーブル","company":"京阪電気鉄道","lastupdate_gmt":1635059765,"source":"鉄道com RSS"},{"name":"特急ラピート","company":"南海電気鉄道","lastupdate_gmt":1635059710,"source":"鉄道com RSS"},{"name":"特急サザン","company":"南海電気鉄道","lastupdate_gmt":1635059710,"source":"鉄道com RSS"},{"name":"飯田線","company":"JR東海","lastupdate_gmt":1635059719,"source":"鉄道com RSS"},{"name":"大糸線","company":"JR西日本","lastupdate_gmt":1635059712,"source":"鉄道com RSS"},{"name":"越後線","company":"JR東日本","lastupdate_gmt":1635059707,"source":"鉄道com RSS"},{"name":"篠ノ井線","company":"JR東日本","lastupdate_gmt":1635059707,"source":"鉄道com RSS"},{"name":"中央本線","company":"JR東日本","lastupdate_gmt":1635059707,"source":"鉄道com RSS"},{"name":"上高地線","company":"アルピコ交通","lastupdate_gmt":1635058855,"source":"鉄道com RSS"}]